bev_legacy/__init__.py
bev_legacy/adjust.py
bev_legacy/adjust_reilly1970.py
bev_legacy/command_line.py
bev_legacy/const.py
bev_legacy/drift_mlr.py
bev_legacy/init.py
bev_legacy/output.py
bev_legacy/plots.py
bev_legacy/schwaus.py
bev_legacy/settings.py
bev_legacy/utils.py
grav_toolbox-0.3.5.dist-info/licenses/LICENSE
gravtools/__init__.py
gravtools/const.py
gravtools/settings.py
gravtools/CG5_utils/__init__.py
gravtools/CG5_utils/cg5_survey.py
gravtools/CG6_utils/__init__.py
gravtools/CG6_utils/cg6_survey.py
gravtools/gui/MainWindow.py
gravtools/gui/__init__.py
gravtools/gui/cumstom_widgets.py
gravtools/gui/dialog_about.py
gravtools/gui/dialog_autoselection_settings.py
gravtools/gui/dialog_calc_drift.py
gravtools/gui/dialog_correction_time_series.py
gravtools/gui/dialog_corrections.py
gravtools/gui/dialog_estimation_settings.py
gravtools/gui/dialog_export_results.py
gravtools/gui/dialog_gis_export_settings.py
gravtools/gui/dialog_load_cg6_obs_files.py
gravtools/gui/dialog_load_stations.py
gravtools/gui/dialog_load_tsf_file.py
gravtools/gui/dialog_new_campaign.py
gravtools/gui/dialog_options.py
gravtools/gui/dialog_setup_data.py
gravtools/gui/dlg_calc_drift.py
gravtools/gui/dlg_correction_time_series.py
gravtools/gui/dlg_corrections.py
gravtools/gui/dlg_export_results.py
gravtools/gui/dlg_load_cg6_obs_files.py
gravtools/gui/dlg_load_tsf_file.py
gravtools/gui/gui_main.py
gravtools/gui/gui_misc.py
gravtools/gui/gui_model_observation_table.py
gravtools/gui/gui_model_results_correlation_matrix_table.py
gravtools/gui/gui_model_results_drift_table.py
gravtools/gui/gui_model_results_obs_table.py
gravtools/gui/gui_model_results_stat_table.py
gravtools/gui/gui_model_results_vg_table.py
gravtools/gui/gui_model_setup_table.py
gravtools/gui/gui_model_station_table.py
gravtools/gui/gui_model_survey_table.py
gravtools/gui/gui_models_gravimeters_scale_table.py
gravtools/gui/survey_table_handler.py
gravtools/models/__init__.py
gravtools/models/atmosphere_correction.py
gravtools/models/campaign.py
gravtools/models/exceptions.py
grav_toolbox-0.3.5.dist-info/METADATA
grav_toolbox-0.3.5.dist-info/WHEEL
grav_toolbox-0.3.5.dist-info/entry_points.txt
grav_toolbox-0.3.5.dist-info/top_level.txt
grav_toolbox-0.3.5.dist-info/zip-safe
grav_toolbox-0.3.5.dist-info/RECORD
