Metadata-Version: 2.4
Name: grav-toolbox
Version: 0.3.5
Summary: Gravity survey utility tools
Home-page: https://github.com/ahellers/GravTools
Author: Andreas Hellerschmied
Author-email: andreas.hellerschmied@bev.gv.at
License: GNU GPLv3
Keywords: gravity,gravimeter,least squares adjustment,geodesy,geophysics
Classifier: License :: OSI Approved :: GNU General Public License v3 (GPLv3)
Classifier: Programming Language :: Python :: 3.8
Classifier: Programming Language :: Python :: 3.9
Classifier: Programming Language :: Python :: 3.10
License-File: LICENSE
Requires-Dist: PyQt5
Requires-Dist: pandas
Requires-Dist: pyqtgraph
Requires-Dist: scipy
Requires-Dist: scikit-learn
Provides-Extra: gis
Requires-Dist: geopandas; extra == "gis"
Dynamic: license-file
